DESCRIPTION.rst
MANIFEST.in
setup.cfg
setup.py
bluesky_libpython/__init__.py
bluesky_libpython/bluesky_cli.py
bluesky_libpython/package_data.dat
bluesky_libpython/testlib.py
bluesky_libpython.egg-info/PKG-INFO
bluesky_libpython.egg-info/SOURCES.txt
bluesky_libpython.egg-info/dependency_links.txt
bluesky_libpython.egg-info/entry_points.txt
bluesky_libpython.egg-info/requires.txt
bluesky_libpython.egg-info/top_level.txt