Metadata-Version: 1.1
Name: bluesky-libpython
Version: 0.0.0
Summary: The testing package version 0.0.0 of client library connecting blue-sky server (The library responds as a browser HTTP client).
Home-page: https://github.com/not001praween001/bluesky-client-libpython.git
Author: Praween AMONTAMAVUT
Author-email: praween@hykwlab.org
License: ISC
Keywords: bluesky
Platform: UNKNOWN
Classifier: Development Status :: 1 - Planning
Classifier: Intended Audience :: Developers
Classifier: Topic :: System
Classifier: License :: OSI Approved :: ISC License (ISCL)
Classifier: Programming Language :: Python :: 2
Classifier: Programming Language :: Python :: 2.6
Classifier: Programming Language :: Python :: 2.7
Classifier: Programming Language :: Python :: 3
Classifier: Programming Language :: Python :: 3.2
Classifier: Programming Language :: Python :: 3.3
Classifier: Programming Language :: Python :: 3.4
